lisa/__init__.py
lisa/_generic.py
lisa/_git.py
lisa/_kmod.py
lisa/_typeclass.py
lisa/_unshare.py
lisa/conf.py
lisa/datautils.py
lisa/energy_meter.py
lisa/energy_model.py
lisa/exekall_customize.py
lisa/fuzz.py
lisa/monad.py
lisa/notebook.py
lisa/pelt.py
lisa/regression.py
lisa/stats.py
lisa/target.py
lisa/test_example.py
lisa/trace.py
lisa/utils.py
lisa/version.py
lisa/wa.py
lisa/wa_results_collector.py
lisa/_assets/__init__.py
lisa/_assets/binaries/arm64/README.dmesg
lisa/_assets/binaries/arm64/README.json-c
lisa/_assets/binaries/arm64/README.libnumactl
lisa/_assets/binaries/arm64/README.libtraceevent
lisa/_assets/binaries/arm64/README.libtracefs
lisa/_assets/binaries/arm64/README.perf
lisa/_assets/binaries/arm64/README.rt-app
lisa/_assets/binaries/arm64/README.taskset
lisa/_assets/binaries/arm64/README.trace-cmd
lisa/_assets/binaries/arm64/dmesg
lisa/_assets/binaries/arm64/pahole
lisa/_assets/binaries/arm64/perf
lisa/_assets/binaries/arm64/rt-app
lisa/_assets/binaries/arm64/sysbench
lisa/_assets/binaries/arm64/taskset
lisa/_assets/binaries/arm64/trace-cmd
lisa/_assets/binaries/armeabi/README.dmesg
lisa/_assets/binaries/armeabi/README.json-c
lisa/_assets/binaries/armeabi/README.libnumactl
lisa/_assets/binaries/armeabi/README.libtraceevent
lisa/_assets/binaries/armeabi/README.libtracefs
lisa/_assets/binaries/armeabi/README.perf
lisa/_assets/binaries/armeabi/README.rt-app
lisa/_assets/binaries/armeabi/README.taskset
lisa/_assets/binaries/armeabi/README.trace-cmd
lisa/_assets/binaries/armeabi/dmesg
lisa/_assets/binaries/armeabi/pahole
lisa/_assets/binaries/armeabi/perf
lisa/_assets/binaries/armeabi/rt-app
lisa/_assets/binaries/armeabi/sysbench
lisa/_assets/binaries/armeabi/taskset
lisa/_assets/binaries/armeabi/trace-cmd
lisa/_assets/binaries/x86_64/README.dmesg
lisa/_assets/binaries/x86_64/README.json-c
lisa/_assets/binaries/x86_64/README.libnumactl
lisa/_assets/binaries/x86_64/README.libtraceevent
lisa/_assets/binaries/x86_64/README.libtracefs
lisa_linux-3.1.0.dist-info/LICENSE.txt
lisa_linux-3.1.0.dist-info/METADATA
lisa_linux-3.1.0.dist-info/WHEEL
lisa_linux-3.1.0.dist-info/entry_points.txt
lisa_linux-3.1.0.dist-info/top_level.txt
lisa_linux-3.1.0.dist-info/RECORD
