Metadata-Version: 2.1
Name: lisa-linux
Version: 3.1.0
Summary: A stick to probe the kernel with
Home-page: https://github.com/ARM-software/lisa
Maintainer: Arm Ltd.
License: Apache License 2.0
Project-URL: Bug Tracker, https://github.com/ARM-software/lisa/issues
Project-URL: Documentation, https://lisa-linux-integrated-system-analysis.readthedocs.io/
Project-URL: Source Code, https://github.com/ARM-software/lisa
Classifier: Programming Language :: Python :: 3 :: Only
Classifier: Operating System :: POSIX :: Linux
Classifier: Topic :: System :: Operating System Kernels :: Linux
Classifier: Topic :: Software Development :: Testing
Classifier: Intended Audience :: Developers
Requires-Python: >= 3.7
License-File: LICENSE.txt
Requires-Dist: psutil (>=4.4.2)
Requires-Dist: matplotlib (>=3.1.0)
Requires-Dist: bokeh
Requires-Dist: selenium
Requires-Dist: phantomjs
Requires-Dist: pillow
Requires-Dist: holoviews
Requires-Dist: panel
Requires-Dist: colorcet
Requires-Dist: pandas (<3.0,>=1.0.0)
Requires-Dist: numpy
Requires-Dist: scipy
Requires-Dist: ruamel.yaml (>=0.16.6)
Requires-Dist: docutils
Requires-Dist: sphobjinv
Requires-Dist: pyarrow
Requires-Dist: ipython
Requires-Dist: ipywidgets
Requires-Dist: devlib (>=1.3.4)
Requires-Dist: jinja2
Requires-Dist: pyelftools
Requires-Dist: cffi
Provides-Extra: all
Requires-Dist: build ; extra == 'all'
Requires-Dist: jupyterlab (>=3) ; extra == 'all'
Requires-Dist: nbsphinx ; extra == 'all'
Requires-Dist: pytest ; extra == 'all'
Requires-Dist: sphinx (>2) ; extra == 'all'
Requires-Dist: sphinx-rtd-theme (>=0.5.2) ; extra == 'all'
Requires-Dist: sphinxcontrib-plantuml ; extra == 'all'
Requires-Dist: twine ; extra == 'all'
Requires-Dist: wlauto ; extra == 'all'
Provides-Extra: dev
Requires-Dist: pytest ; extra == 'dev'
Requires-Dist: build ; extra == 'dev'
Requires-Dist: twine ; extra == 'dev'
Provides-Extra: doc
Requires-Dist: sphinx (>2) ; extra == 'doc'
Requires-Dist: sphinx-rtd-theme (>=0.5.2) ; extra == 'doc'
Requires-Dist: sphinxcontrib-plantuml ; extra == 'doc'
Requires-Dist: nbsphinx ; extra == 'doc'
Requires-Dist: jupyterlab (>=3) ; extra == 'doc'
Requires-Dist: pytest ; extra == 'doc'
Requires-Dist: build ; extra == 'doc'
Requires-Dist: twine ; extra == 'doc'
Requires-Dist: wlauto ; extra == 'doc'
Provides-Extra: notebook
Requires-Dist: jupyterlab (>=3) ; extra == 'notebook'
Provides-Extra: wa
Requires-Dist: wlauto ; extra == 'wa'
